repler/__init__.py
repler/repler.py
repler-1.0.1.dist-info/METADATA
repler-1.0.1.dist-info/WHEEL
repler-1.0.1.dist-info/licenses/LICENSE
repler-1.0.1.dist-info/RECORD
