Metadata-Version: 2.1
Name: repler
Version: 1.0.1
Summary: The tool keeps you project envieronment clean by delete or archive files with specified extensions.
Project-URL: Homepage, https://github.com/abarzilai/report-handler/tree/main
Project-URL: Bug Tracker, https://github.com/abarzilai/report-handler/issues
Author-email: Alexander Barzilai <Alex74zel@gmail.com>
License-File: LICENSE
Classifier: License :: OSI Approved :: MIT License
Classifier: Operating System :: OS Independent
Classifier: Programming Language :: Python :: 3
Requires-Python: >=3.7
